LICENSE
MANIFEST.in
README.rst
README_CH.rst
VERSION
requirements.txt
setup.py
common_cache/__init__.py
common_cache/cleanup.py
common_cache/eviction.py
python_common_cache.egg-info/PKG-INFO
python_common_cache.egg-info/SOURCES.txt
python_common_cache.egg-info/dependency_links.txt
python_common_cache.egg-info/top_level.txt