Metadata-Version: 1.1
Name: python-common-cache
Version: 0.1
Summary: This project is an cache component based on the memory and it is lightweight, simple and customizable, you can implement a cache that your needs in a very simple way.
Home-page: https://github.com/SylvanasSun/python-common-cache
Author: SylvanasSun
Author-email: sylvanas.sun@gmail.com
License: MIT
Keywords: python cache utils
Platform: UNKNOWN
Classifier: Development Status :: 4 - Beta
Classifier: Intended Audience :: Developers
Classifier: License :: OSI Approved :: MIT License
Classifier: Programming Language :: Python :: 3.4
Classifier: Programming Language :: Python :: 3.5
Classifier: Programming Language :: Python :: 3.6
